<?xml version="1.0" encoding="Windows-1252"?>
<HighScore xmlns:xsi="http://www.w3.org/2001/XMLSchema-instance" xmlns:xsd="http://www.w3.org/2001/XMLSchema">
  <DailyScores />
  <weeklyScores>
    <ScoreXML>
      <score>6</score>
      <time>2014-09-15T10:07:11.3467151-07:00</time>
    </ScoreXML>
    <ScoreXML>
      <score>2</score>
      <time>2014-09-15T10:07:11.3657162-07:00</time>
    </ScoreXML>
  </weeklyScores>
  <monthlyScores>
    <ScoreXML>
      <score>6</score>
      <time>2014-09-15T10:07:11.3467151-07:00</time>
    </ScoreXML>
    <ScoreXML>
      <score>2</score>
      <time>2014-09-15T10:07:11.3657162-07:00</time>
    </ScoreXML>
  </monthlyScores>
</HighScore>